{
  "frames": {
    "Bosque__castillo__g1923": {
      "frame": {
        "x": 0,
        "y": 0,
        "w": 992,
        "h": 1658
      },
      "rotated": false,
      "trimmed": false,
      "spriteSourceSize": {
        "x": 0,
        "y": 0,
        "w": 992,
        "h": 1658
      },
      "sourceSize": {
        "w": 992,
        "h": 1658
      }
    },
    "puerto_viejo__piedras_esquina__g692-2": {
      "frame": {
        "x": 994,
        "y": 0,
        "w": 905,
        "h": 1079
      },
      "rotated": false,
      "trimmed": false,
      "spriteSourceSize": {
        "x": 0,
        "y": 0,
        "w": 905,
        "h": 1079
      },
      "sourceSize": {
        "w": 905,
        "h": 1079
      }
    },
    "Juegos__puntos__path2635": {
      "frame": {
        "x": 994,
        "y": 1081,
        "w": 999,
        "h": 411
      },
      "rotated": false,
      "trimmed": false,
      "spriteSourceSize": {
        "x": 0,
        "y": 0,
        "w": 999,
        "h": 411
      },
      "sourceSize": {
        "w": 999,
        "h": 411
      }
    },
    "Bosque__path2767__path2767": {
      "frame": {
        "x": 0,
        "y": 1660,
        "w": 846,
        "h": 385
      },
      "rotated": false,
      "trimmed": false,
      "spriteSourceSize": {
        "x": 0,
        "y": 0,
        "w": 846,
        "h": 385
      },
      "sourceSize": {
        "w": 846,
        "h": 385
      }
    },
    "Juegos__path967-0-03-5__path967-0-03-5": {
      "frame": {
        "x": 848,
        "y": 1660,
        "w": 648,
        "h": 372
      },
      "rotated": false,
      "trimmed": false,
      "spriteSourceSize": {
        "x": 0,
        "y": 0,
        "w": 648,
        "h": 372
      },
      "sourceSize": {
        "w": 648,
        "h": 372
      }
    },
    "costa__castro__g1608": {
      "frame": {
        "x": 1498,
        "y": 1660,
        "w": 492,
        "h": 360
      },
      "rotated": false,
      "trimmed": false,
      "spriteSourceSize": {
        "x": 0,
        "y": 0,
        "w": 492,
        "h": 360
      },
      "sourceSize": {
        "w": 492,
        "h": 360
      }
    },
    "Puerto__mono_paleta__g222": {
      "frame": {
        "x": 1901,
        "y": 0,
        "w": 144,
        "h": 343
      },
      "rotated": false,
      "trimmed": false,
      "spriteSourceSize": {
        "x": 0,
        "y": 0,
        "w": 144,
        "h": 343
      },
      "sourceSize": {
        "w": 144,
        "h": 343
      }
    },
    "Mar__mono_pepe__g1128": {
      "frame": {
        "x": 1901,
        "y": 345,
        "w": 143,
        "h": 249
      },
      "rotated": false,
      "trimmed": false,
      "spriteSourceSize": {
        "x": 0,
        "y": 0,
        "w": 143,
        "h": 249
      },
      "sourceSize": {
        "w": 143,
        "h": 249
      }
    },
    "Mar__mono_eloy__g1104": {
      "frame": {
        "x": 1901,
        "y": 596,
        "w": 126,
        "h": 229
      },
      "rotated": false,
      "trimmed": false,
      "spriteSourceSize": {
        "x": 0,
        "y": 0,
        "w": 126,
        "h": 229
      },
      "sourceSize": {
        "w": 126,
        "h": 229
      }
    },
    "Puerto__mono_luisa__g94": {
      "frame": {
        "x": 1901,
        "y": 827,
        "w": 128,
        "h": 227
      },
      "rotated": false,
      "trimmed": false,
      "spriteSourceSize": {
        "x": 0,
        "y": 0,
        "w": 128,
        "h": 227
      },
      "sourceSize": {
        "w": 128,
        "h": 227
      }
    },
    "Puerto__noray__g950": {
      "frame": {
        "x": 994,
        "y": 1494,
        "w": 213,
        "h": 155
      },
      "rotated": false,
      "trimmed": false,
      "spriteSourceSize": {
        "x": 0,
        "y": 0,
        "w": 213,
        "h": 155
      },
      "sourceSize": {
        "w": 213,
        "h": 155
      }
    },
    "Mar__ob_caja_plastico__g89": {
      "frame": {
        "x": 1209,
        "y": 1494,
        "w": 190,
        "h": 138
      },
      "rotated": false,
      "trimmed": false,
      "spriteSourceSize": {
        "x": 0,
        "y": 0,
        "w": 190,
        "h": 138
      },
      "sourceSize": {
        "w": 190,
        "h": 138
      }
    },
    "Puerto__ob_caja_porex_cerrada__g262": {
      "frame": {
        "x": 1401,
        "y": 1494,
        "w": 153,
        "h": 120
      },
      "rotated": false,
      "trimmed": false,
      "spriteSourceSize": {
        "x": 0,
        "y": 0,
        "w": 153,
        "h": 120
      },
      "sourceSize": {
        "w": 153,
        "h": 120
      }
    },
    "puerto_viejo__ob_caja_porex_vino__g278": {
      "frame": {
        "x": 1556,
        "y": 1494,
        "w": 152,
        "h": 110
      },
      "rotated": false,
      "trimmed": false,
      "spriteSourceSize": {
        "x": 0,
        "y": 0,
        "w": 152,
        "h": 110
      },
      "sourceSize": {
        "w": 152,
        "h": 110
      }
    },
    "plaza__ob_alcantarilla__g682-1": {
      "frame": {
        "x": 1710,
        "y": 1494,
        "w": 148,
        "h": 109
      },
      "rotated": false,
      "trimmed": false,
      "spriteSourceSize": {
        "x": 0,
        "y": 0,
        "w": 148,
        "h": 109
      },
      "sourceSize": {
        "w": 148,
        "h": 109
      }
    },
    "Playa__ob_alcantarilla__g682": {
      "frame": {
        "x": 1860,
        "y": 1494,
        "w": 148,
        "h": 99
      },
      "rotated": false,
      "trimmed": false,
      "spriteSourceSize": {
        "x": 0,
        "y": 0,
        "w": 148,
        "h": 99
      },
      "sourceSize": {
        "w": 148,
        "h": 99
      }
    }
  },
  "meta": {
    "app": "boiro split atlas generator",
    "version": "1.0",
    "image": "atlas-23.png",
    "format": "RGBA8888",
    "size": {
      "w": 2048,
      "h": 2048
    },
    "scale": "1"
  },
  "sprites": [
    {
      "label": "Playa",
      "children": [
        {
          "label": "Playa__ob_alcantarilla__g682",
          "frame": "Playa__ob_alcantarilla__g682",
          "bounds": {
            "x": 2077,
            "y": 458,
            "width": 148,
            "height": 99
          }
        }
      ]
    },
    {
      "label": "Mar",
      "children": [
        {
          "label": "Mar__mono_eloy__g1104",
          "frame": "Mar__mono_eloy__g1104",
          "bounds": {
            "x": 2282,
            "y": 2204,
            "width": 126,
            "height": 229
          }
        },
        {
          "label": "Mar__mono_pepe__g1128",
          "frame": "Mar__mono_pepe__g1128",
          "bounds": {
            "x": 2898,
            "y": 2206,
            "width": 143,
            "height": 249
          }
        },
        {
          "label": "Mar__ob_caja_plastico__g89",
          "frame": "Mar__ob_caja_plastico__g89",
          "bounds": {
            "x": 2408,
            "y": 2321,
            "width": 190,
            "height": 138
          }
        }
      ]
    },
    {
      "label": "Juegos",
      "children": [
        {
          "label": "Juegos__puntos__path2635",
          "frame": "Juegos__puntos__path2635",
          "bounds": {
            "x": 2117,
            "y": 0,
            "width": 999,
            "height": 411
          }
        },
        {
          "label": "Juegos__path967-0-03-5__path967-0-03-5",
          "frame": "Juegos__path967-0-03-5__path967-0-03-5",
          "bounds": {
            "x": 2491,
            "y": 0,
            "width": 648,
            "height": 372
          }
        }
      ]
    },
    {
      "label": "plaza",
      "children": [
        {
          "label": "plaza__ob_alcantarilla__g682-1",
          "frame": "plaza__ob_alcantarilla__g682-1",
          "bounds": {
            "x": 3429,
            "y": 1158,
            "width": 148,
            "height": 109
          }
        }
      ]
    },
    {
      "label": "Puerto",
      "children": [
        {
          "label": "Puerto__mono_luisa__g94",
          "frame": "Puerto__mono_luisa__g94",
          "bounds": {
            "x": 4137,
            "y": 1027,
            "width": 128,
            "height": 227
          }
        },
        {
          "label": "Puerto__mono_paleta__g222",
          "frame": "Puerto__mono_paleta__g222",
          "bounds": {
            "x": 4701,
            "y": 1304,
            "width": 144,
            "height": 343
          }
        },
        {
          "label": "Puerto__ob_caja_porex_cerrada__g262",
          "frame": "Puerto__ob_caja_porex_cerrada__g262",
          "bounds": {
            "x": 4416,
            "y": 988,
            "width": 153,
            "height": 120
          }
        },
        {
          "label": "Puerto__noray__g950",
          "frame": "Puerto__noray__g950",
          "bounds": {
            "x": 4338,
            "y": 1927,
            "width": 213,
            "height": 155
          }
        }
      ]
    },
    {
      "label": "puerto_viejo",
      "children": [
        {
          "label": "puerto_viejo__piedras_esquina__g692-2",
          "frame": "puerto_viejo__piedras_esquina__g692-2",
          "bounds": {
            "x": 5474,
            "y": 1186,
            "width": 905,
            "height": 1079
          }
        },
        {
          "label": "puerto_viejo__ob_caja_porex_vino__g278",
          "frame": "puerto_viejo__ob_caja_porex_vino__g278",
          "bounds": {
            "x": 2538,
            "y": 2452,
            "width": 152,
            "height": 110
          }
        }
      ]
    },
    {
      "label": "Bosque",
      "children": [
        {
          "label": "Bosque__castillo__g1923",
          "frame": "Bosque__castillo__g1923",
          "bounds": {
            "x": 5811,
            "y": 0,
            "width": 992,
            "height": 1658
          }
        },
        {
          "label": "Bosque__path2767__path2767",
          "frame": "Bosque__path2767__path2767",
          "bounds": {
            "x": 4466,
            "y": 7,
            "width": 846,
            "height": 385
          }
        }
      ]
    },
    {
      "label": "costa",
      "children": [
        {
          "label": "costa__castro__g1608",
          "frame": "costa__castro__g1608",
          "bounds": {
            "x": 5848,
            "y": 2281,
            "width": 492,
            "height": 360
          }
        }
      ]
    }
  ]
}
